<?xml version='1.0' encoding='utf-8'?>
<TextureAtlas imagePath="GooeyCar.png">
<SubTexture name="left0000" x="0" y="0" width="271" height="324" frameX="-16" frameY="-52" frameWidth="400" frameHeight="400" />
<SubTexture name="left0001" x="271" y="0" width="268" height="325" frameX="-18" frameY="-51" frameWidth="400" frameHeight="400" />
<SubTexture name="left0002" x="539" y="0" width="273" height="322" frameX="-19" frameY="-54" frameWidth="400" frameHeight="400" />
<SubTexture name="left0003" x="812" y="0" width="271" height="323" frameX="-20" frameY="-53" frameWidth="400" frameHeight="400" />
<SubTexture name="left0004" x="1083" y="0" width="273" height="322" frameX="-22" frameY="-54" frameWidth="400" frameHeight="400" />
<SubTexture name="left0005" x="1356" y="0" width="275" height="321" frameX="-21" frameY="-55" frameWidth="400" frameHeight="400" />
<SubTexture name="left0006" x="1631" y="0" width="272" height="322" frameX="-23" frameY="-54" frameWidth="400" frameHeight="400" />
<SubTexture name="left0007" x="0" y="325" width="271" height="322" frameX="-22" frameY="-54" frameWidth="400" frameHeight="400" />
<SubTexture name="right0000" x="271" y="325" width="301" height="322" frameX="-50" frameY="-55" frameWidth="400" frameHeight="400" />
<SubTexture name="right0001" x="572" y="325" width="303" height="321" frameX="-49" frameY="-56" frameWidth="400" frameHeight="400" />
<SubTexture name="right0002" x="875" y="325" width="299" height="321" frameX="-48" frameY="-56" frameWidth="400" frameHeight="400" />
<SubTexture name="right0003" x="1174" y="325" width="294" height="322" frameX="-50" frameY="-55" frameWidth="400" frameHeight="400" />
<SubTexture name="right0004" x="1468" y="325" width="297" height="321" frameX="-45" frameY="-56" frameWidth="400" frameHeight="400" />
<SubTexture name="right0005" x="1765" y="325" width="297" height="320" frameX="-46" frameY="-57" frameWidth="400" frameHeight="400" />
<SubTexture name="right0006" x="0" y="647" width="298" height="321" frameX="-44" frameY="-56" frameWidth="400" frameHeight="400" />
<SubTexture name="right0007" x="298" y="647" width="295" height="321" frameX="-45" frameY="-56" frameWidth="400" frameHeight="400" />
<SubTexture name="up0000" x="593" y="647" width="282" height="308" frameX="-33" frameY="-69" frameWidth="400" frameHeight="400" />
<SubTexture name="up0001" x="875" y="647" width="281" height="306" frameX="-32" frameY="-71" frameWidth="400" frameHeight="400" />
<SubTexture name="up0002" x="1156" y="647" width="282" height="304" frameX="-32" frameY="-73" frameWidth="400" frameHeight="400" />
<SubTexture name="up0003" x="1438" y="647" width="288" height="301" frameX="-30" frameY="-76" frameWidth="400" frameHeight="400" />
<SubTexture name="up0004" x="1726" y="647" width="287" height="297" frameX="-29" frameY="-80" frameWidth="400" frameHeight="400" />
<SubTexture name="up0005" x="0" y="968" width="287" height="295" frameX="-28" frameY="-82" frameWidth="400" frameHeight="400" />
<SubTexture name="up0006" x="287" y="968" width="282" height="299" frameX="-31" frameY="-78" frameWidth="400" frameHeight="400" />
<SubTexture name="up0007" x="569" y="968" width="291" height="296" frameX="-27" frameY="-81" frameWidth="400" frameHeight="400" />
<SubTexture name="down0000" x="860" y="968" width="308" height="265" frameX="-73" frameY="-127" frameWidth="400" frameHeight="400" />
<SubTexture name="down0001" x="1168" y="968" width="310" height="264" frameX="-73" frameY="-128" frameWidth="400" frameHeight="400" />
<SubTexture name="down0002" x="1478" y="968" width="308" height="269" frameX="-72" frameY="-124" frameWidth="400" frameHeight="400" />
<SubTexture name="down0003" x="1786" y="968" width="307" height="269" frameX="-71" frameY="-124" frameWidth="400" frameHeight="400" />
<SubTexture name="down0004" x="0" y="1267" width="308" height="276" frameX="-71" frameY="-117" frameWidth="400" frameHeight="400" />
<SubTexture name="down0005" x="308" y="1267" width="309" height="274" frameX="-71" frameY="-119" frameWidth="400" frameHeight="400" />
<SubTexture name="down0006" x="617" y="1267" width="307" height="275" frameX="-72" frameY="-118" frameWidth="400" frameHeight="400" />
<SubTexture name="down0007" x="924" y="1267" width="306" height="275" frameX="-71" frameY="-118" frameWidth="400" frameHeight="400" />
<SubTexture name="idle0000" x="1230" y="1267" width="285" height="304" frameX="-35" frameY="-73" frameWidth="400" frameHeight="400" />
<SubTexture name="idle0001" x="1515" y="1267" width="288" height="304" frameX="-32" frameY="-73" frameWidth="400" frameHeight="400" />
<SubTexture name="idle0002" x="1803" y="1267" width="285" height="303" frameX="-35" frameY="-74" frameWidth="400" frameHeight="400" />
<SubTexture name="idle0003" x="0" y="1571" width="288" height="301" frameX="-33" frameY="-76" frameWidth="400" frameHeight="400" />
<SubTexture name="idle0004" x="288" y="1571" width="281" height="312" frameX="-39" frameY="-65" frameWidth="400" frameHeight="400" />
<SubTexture name="idle0005" x="569" y="1571" width="281" height="312" frameX="-37" frameY="-65" frameWidth="400" frameHeight="400" />
<SubTexture name="idle0006" x="850" y="1571" width="280" height="313" frameX="-40" frameY="-64" frameWidth="400" frameHeight="400" />
<SubTexture name="idle0007" x="1130" y="1571" width="283" height="311" frameX="-38" frameY="-66" frameWidth="400" frameHeight="400" />
<SubTexture name="idle0008" x="1413" y="1571" width="280" height="323" frameX="-39" frameY="-54" frameWidth="400" frameHeight="400" />
<SubTexture name="idle0009" x="1693" y="1571" width="279" height="323" frameX="-38" frameY="-54" frameWidth="400" frameHeight="400" />
<SubTexture name="idle0010" x="0" y="1894" width="280" height="325" frameX="-38" frameY="-52" frameWidth="400" frameHeight="400" />
<SubTexture name="idle0011" x="280" y="1894" width="284" height="325" frameX="-36" frameY="-52" frameWidth="400" frameHeight="400" />
<SubTexture name="idle0012" x="564" y="1894" width="280" height="325" frameX="-39" frameY="-52" frameWidth="400" frameHeight="400" />
<SubTexture name="idle0013" x="844" y="1894" width="279" height="325" frameX="-38" frameY="-52" frameWidth="400" frameHeight="400" />
<SubTexture name="missedl0000" x="1123" y="1894" width="297" height="338" frameX="-3" frameY="-39" frameWidth="400" frameHeight="400" />
<SubTexture name="missedl0001" x="1420" y="1894" width="273" height="323" frameX="-22" frameY="-53" frameWidth="400" frameHeight="400" />
<SubTexture name="missedr0000" x="1693" y="1894" width="309" height="346" frameX="-43" frameY="-34" frameWidth="400" frameHeight="400" />
<SubTexture name="missedr0001" x="0" y="2240" width="297" height="324" frameX="-45" frameY="-53" frameWidth="400" frameHeight="400" />
<SubTexture name="missedu0000" x="297" y="2240" width="305" height="346" frameX="-14" frameY="-34" frameWidth="400" frameHeight="400" />
<SubTexture name="missedu0001" x="602" y="2240" width="287" height="326" frameX="-29" frameY="-51" frameWidth="400" frameHeight="400" />
<SubTexture name="missedd0000" x="889" y="2240" width="329" height="300" frameX="-59" frameY="-95" frameWidth="400" frameHeight="400" />
<SubTexture name="missedd0001" x="1218" y="2240" width="307" height="291" frameX="-71" frameY="-101" frameWidth="400" frameHeight="400" />
</TextureAtlas>
