<?xml version="0.5" encoding="utf-8"?>
<TextureAtlas imagePath="PibbyTwilight_Laser.png">
	<!-- Created with Adobe Animate version 22.0.2.168 -->
	<!-- http://www.adobe.com/products/animate.html -->
	<SubTexture name="Twi_Charge_LASER instance 10000" x="0" y="0" width="269" height="267.5" frameX="-28" frameY="-57.5" frameWidth="318" frameHeight="325.5"/>
	<SubTexture name="Twi_Charge_LASER instance 10001" x="294" y="0" width="291.5" height="265.5" frameX="-15" frameY="-60" frameWidth="318" frameHeight="325.5"/>
	<SubTexture name="Twi_Charge_LASER instance 10002" x="610.5" y="0" width="306" height="297" frameX="-7" frameY="-28" frameWidth="318" frameHeight="325.5"/>
	<SubTexture name="Twi_Charge_LASER instance 10003" x="941.5" y="0" width="282" height="315.5" frameX="-2.5" frameY="-9.5" frameWidth="318" frameHeight="325.5"/>
	<SubTexture name="Twi_Charge_LASER instance 10004" x="1248.5" y="0" width="294" height="299" frameX="-0.5" frameY="-26" frameWidth="318" frameHeight="325.5"/>
	<SubTexture name="Twi_Charge_LASER instance 10005" x="1567.5" y="0" width="279" height="314.5" frameX="0" frameY="-10.5" frameWidth="318" frameHeight="325.5"/>
	<SubTexture name="Twi_Charge_LASER instance 10006" x="1871.5" y="0" width="285" height="325" frameX="-0.5" frameY="0" frameWidth="318" frameHeight="325.5"/>
	<SubTexture name="Twi_Charge_LASER instance 10007" x="2181.5" y="0" width="287" height="295.5" frameX="-1" frameY="-29.5" frameWidth="318" frameHeight="325.5"/>
	<SubTexture name="Twi_Charge_LASER instance 10008" x="2493.5" y="0" width="302.5" height="295" frameX="-2" frameY="-30" frameWidth="318" frameHeight="325.5"/>
	<SubTexture name="Twi_Charge_LASER instance 10009" x="2821" y="0" width="286" height="311" frameX="-2" frameY="-14" frameWidth="318" frameHeight="325.5"/>
	<SubTexture name="Twi_Charge_LASER instance 10010" x="3132" y="0" width="291.5" height="324.5" frameX="-2" frameY="-0.5" frameWidth="318" frameHeight="325.5"/>
	<SubTexture name="Twi_Charge_LASER instance 10011" x="3448.5" y="0" width="289" height="296" frameX="-2" frameY="-29" frameWidth="318" frameHeight="325.5"/>
	<SubTexture name="Twi_Charge_LASER instance 10012" x="3762.5" y="0" width="301" height="296.5" frameX="-2" frameY="-28.5" frameWidth="318" frameHeight="325.5"/>
	<SubTexture name="Twi_Charge_LASER instance 10013" x="0" y="350" width="285.5" height="312" frameX="-2" frameY="-13" frameWidth="318" frameHeight="325.5"/>
	<SubTexture name="Twi_Charge_LASER instance 10014" x="310.5" y="350" width="291.5" height="324.5" frameX="-2" frameY="-0.5" frameWidth="318" frameHeight="325.5"/>
	<SubTexture name="Twi_Charge_LASER instance 10015" x="627" y="350" width="314.5" height="306" frameX="-3.5" frameY="-19" frameWidth="318" frameHeight="325.5"/>
	<SubTexture name="Twi_Charge_LASER instance 10016" x="966.5" y="350" width="304.5" height="282" frameX="-3.5" frameY="-43" frameWidth="318" frameHeight="325.5"/>
	<SubTexture name="Twi_Down_LASER instance 10000" x="1296" y="350" width="266.5" height="262" frameX="-136" frameY="0" frameWidth="452.5" frameHeight="311.5"/>
	<SubTexture name="Twi_Down_LASER instance 10001" x="1587.5" y="350" width="404.5" height="219" frameX="-48" frameY="-50.5" frameWidth="452.5" frameHeight="311.5"/>
	<SubTexture name="Twi_Down_LASER instance 10002" x="2017" y="350" width="450.5" height="214.5" frameX="0" frameY="-52.5" frameWidth="452.5" frameHeight="311.5"/>
	<SubTexture name="Twi_Down_LASER instance 10003" x="2492.5" y="350" width="441" height="220" frameX="-2" frameY="-48" frameWidth="452.5" frameHeight="311.5"/>
	<SubTexture name="Twi_Down_LASER instance 10004" x="2958.5" y="350" width="387.5" height="262.5" frameX="-53" frameY="-49" frameWidth="452.5" frameHeight="311.5"/>
	<SubTexture name="Twi_Down_LASER instance 10005" x="3371" y="350" width="378.5" height="261" frameX="-62" frameY="-50" frameWidth="452.5" frameHeight="311.5"/>
	<SubTexture name="Twi_HEHEHE_LASER instance 10000" x="3774.5" y="350" width="241" height="294" frameX="-7.5" frameY="-6.5" frameWidth="248.5" frameHeight="300.5"/>
	<SubTexture name="Twi_HEHEHE_LASER instance 10001" x="0" y="699.5" width="242" height="290" frameX="-3" frameY="-10.5" frameWidth="248.5" frameHeight="300.5"/>
	<SubTexture name="Twi_HEHEHE_LASER instance 10002" x="267" y="699.5" width="240.5" height="286" frameX="-1.5" frameY="-14.5" frameWidth="248.5" frameHeight="300.5"/>
	<SubTexture name="Twi_HEHEHE_LASER instance 10003" x="532.5" y="699.5" width="239" height="292" frameX="-1" frameY="-8.5" frameWidth="248.5" frameHeight="300.5"/>
	<SubTexture name="Twi_HEHEHE_LASER instance 10004" x="796.5" y="699.5" width="239.5" height="296" frameX="-0.5" frameY="-4.5" frameWidth="248.5" frameHeight="300.5"/>
	<SubTexture name="Twi_HEHEHE_LASER instance 10005" x="1061" y="699.5" width="239.5" height="290.5" frameX="0" frameY="-10" frameWidth="248.5" frameHeight="300.5"/>
	<SubTexture name="Twi_HEHEHE_LASER instance 10006" x="1325.5" y="699.5" width="239.5" height="287" frameX="-0.5" frameY="-13.5" frameWidth="248.5" frameHeight="300.5"/>
	<SubTexture name="Twi_HEHEHE_LASER instance 10007" x="1590" y="699.5" width="239.5" height="293" frameX="-0.5" frameY="-7.5" frameWidth="248.5" frameHeight="300.5"/>
	<SubTexture name="Twi_HEHEHE_LASER instance 10008" x="1854.5" y="699.5" width="239.5" height="300.5" frameX="-0.5" frameY="0" frameWidth="248.5" frameHeight="300.5"/>
	<SubTexture name="Twi_HEHEHE_LASER instance 10009" x="2119" y="699.5" width="239" height="299.5" frameX="-1" frameY="-1" frameWidth="248.5" frameHeight="300.5"/>
	<SubTexture name="Twi_HEHEHE_LASER instance 10010" x="2383" y="699.5" width="239" height="299" frameX="-1.5" frameY="-1.5" frameWidth="248.5" frameHeight="300.5"/>
	<SubTexture name="Twi_HEHEHE_LASER instance 10011" x="2647" y="699.5" width="239" height="297.5" frameX="-2" frameY="-3" frameWidth="248.5" frameHeight="300.5"/>
	<SubTexture name="Twi_HEHEHE_LASER instance 10012" x="2911" y="699.5" width="239" height="293.5" frameX="-3" frameY="-7" frameWidth="248.5" frameHeight="300.5"/>
	<SubTexture name="Twi_HEHEHE_LASER instance 10013" x="3175" y="699.5" width="238" height="289.5" frameX="-4.5" frameY="-11" frameWidth="248.5" frameHeight="300.5"/>
	<SubTexture name="Twi_HEHEHE_LASER instance 10014" x="3438" y="699.5" width="237.5" height="287" frameX="-6" frameY="-13.5" frameWidth="248.5" frameHeight="300.5"/>
	<SubTexture name="Twi_HEHEHE_LASER instance 10015" x="3700.5" y="699.5" width="241" height="285.5" frameX="-7.5" frameY="-15" frameWidth="248.5" frameHeight="300.5"/>
	<SubTexture name="Twi_HEHEHE_LASER instance 10016" x="0" y="1025" width="241" height="285.5" frameX="-7.5" frameY="-15" frameWidth="248.5" frameHeight="300.5"/>
	<SubTexture name="Twi_HEHEHE_LASER instance 10017" x="266" y="1025" width="241" height="285.5" frameX="-7.5" frameY="-15" frameWidth="248.5" frameHeight="300.5"/>
	<SubTexture name="Twi_HEHEHE_LASER instance 10018" x="532" y="1025" width="241" height="286" frameX="-7.5" frameY="-14.5" frameWidth="248.5" frameHeight="300.5"/>
	<SubTexture name="Twi_HEHEHE_LASER instance 10019" x="798" y="1025" width="241" height="285.5" frameX="-7.5" frameY="-15" frameWidth="248.5" frameHeight="300.5"/>
	<SubTexture name="Twi_Idle_LASER instance 10000" x="1064" y="1025" width="285.5" height="260.5" frameX="-1" frameY="-17" frameWidth="288.5" frameHeight="277.5"/>
	<SubTexture name="Twi_Idle_LASER instance 10001" x="1374.5" y="1025" width="281" height="251.5" frameX="-7.5" frameY="-26" frameWidth="288.5" frameHeight="277.5"/>
	<SubTexture name="Twi_Idle_LASER instance 10002" x="1680.5" y="1025" width="277" height="257" frameX="-4.5" frameY="-20.5" frameWidth="288.5" frameHeight="277.5"/>
	<SubTexture name="Twi_Idle_LASER instance 10003" x="1982.5" y="1025" width="273.5" height="262" frameX="-2.5" frameY="-15.5" frameWidth="288.5" frameHeight="277.5"/>
	<SubTexture name="Twi_Idle_LASER instance 10004" x="2281" y="1025" width="272" height="272" frameX="-1.5" frameY="-5.5" frameWidth="288.5" frameHeight="277.5"/>
	<SubTexture name="Twi_Idle_LASER instance 10005" x="2578" y="1025" width="271" height="274" frameX="-0.5" frameY="-3.5" frameWidth="288.5" frameHeight="277.5"/>
	<SubTexture name="Twi_Idle_LASER instance 10006" x="2874" y="1025" width="270" height="276.5" frameX="0" frameY="-1" frameWidth="288.5" frameHeight="277.5"/>
	<SubTexture name="Twi_Idle_LASER instance 10007" x="3169" y="1025" width="269.5" height="277.5" frameX="0" frameY="0" frameWidth="288.5" frameHeight="277.5"/>
	<SubTexture name="Twi_Idle_LASER instance 10008" x="3463.5" y="1025" width="269.5" height="276.5" frameX="0" frameY="-1" frameWidth="288.5" frameHeight="277.5"/>
	<SubTexture name="Twi_Idle_LASER instance 10009" x="3758" y="1025" width="269.5" height="276.5" frameX="0" frameY="-1" frameWidth="288.5" frameHeight="277.5"/>
	<SubTexture name="Twi_Idle_LASER instance 10010" x="0" y="1336" width="270.5" height="276" frameX="0" frameY="-1.5" frameWidth="288.5" frameHeight="277.5"/>
	<SubTexture name="Twi_Idle_LASER instance 10011" x="295.5" y="1336" width="271.5" height="276" frameX="0" frameY="-1.5" frameWidth="288.5" frameHeight="277.5"/>
	<SubTexture name="Twi_Idle_LASER instance 10012" x="592" y="1336" width="271.5" height="276.5" frameX="0" frameY="-1" frameWidth="288.5" frameHeight="277.5"/>
	<SubTexture name="Twi_Idle_LASER instance 10013" x="888.5" y="1336" width="271.5" height="276.5" frameX="0" frameY="-1" frameWidth="288.5" frameHeight="277.5"/>
	<SubTexture name="Twi_Idle_LASER instance 10014" x="1185" y="1336" width="271.5" height="270.5" frameX="0" frameY="-7" frameWidth="288.5" frameHeight="277.5"/>
	<SubTexture name="Twi_Idle_LASER instance 10015" x="1481.5" y="1336" width="271.5" height="270" frameX="0" frameY="-7.5" frameWidth="288.5" frameHeight="277.5"/>
	<SubTexture name="Twi_Idle_LASER instance 10016" x="1778" y="1336" width="271.5" height="270" frameX="0" frameY="-7.5" frameWidth="288.5" frameHeight="277.5"/>
	<SubTexture name="Twi_Idle_LASER instance 10017" x="2074.5" y="1336" width="271.5" height="270.5" frameX="0" frameY="-7" frameWidth="288.5" frameHeight="277.5"/>
	<SubTexture name="Twi_Idle_LASER instance 10018" x="2371" y="1336" width="271.5" height="271" frameX="0" frameY="-6.5" frameWidth="288.5" frameHeight="277.5"/>
	<SubTexture name="Twi_Idle_LASER instance 10019" x="2667.5" y="1336" width="271.5" height="271" frameX="0" frameY="-6.5" frameWidth="288.5" frameHeight="277.5"/>
	<SubTexture name="Twi_Idle_LASER instance 10020" x="2964" y="1336" width="271.5" height="271" frameX="0" frameY="-6.5" frameWidth="288.5" frameHeight="277.5"/>
	<SubTexture name="Twi_Idle_LASER instance 10021" x="3260.5" y="1336" width="271.5" height="271.5" frameX="0" frameY="-6" frameWidth="288.5" frameHeight="277.5"/>
	<SubTexture name="Twi_Idle_LASER instance 10022" x="3557" y="1336" width="271.5" height="271.5" frameX="0" frameY="-6" frameWidth="288.5" frameHeight="277.5"/>
	<SubTexture name="Twi_Left_LASER instance 10000" x="3853.5" y="1336" width="234" height="238.5" frameX="-4.5" frameY="-33.5" frameWidth="239" frameHeight="272"/>
	<SubTexture name="Twi_Left_LASER instance 10001" x="0" y="1637.5" width="235" height="259.5" frameX="-4" frameY="-7.5" frameWidth="239" frameHeight="272"/>
	<SubTexture name="Twi_Left_LASER instance 10002" x="260" y="1637.5" width="237.5" height="264" frameX="-1.5" frameY="-3" frameWidth="239" frameHeight="272"/>
	<SubTexture name="Twi_Left_LASER instance 10003" x="522.5" y="1637.5" width="239" height="265" frameX="0" frameY="-2" frameWidth="239" frameHeight="272"/>
	<SubTexture name="Twi_Left_LASER instance 10004" x="786.5" y="1637.5" width="239" height="267" frameX="0" frameY="0" frameWidth="239" frameHeight="272"/>
	<SubTexture name="Twi_Left_LASER instance 10005" x="1050.5" y="1637.5" width="238" height="265" frameX="-1" frameY="-2" frameWidth="239" frameHeight="272"/>
	<SubTexture name="Twi_Right_LASER instance 10000" x="1313.5" y="1637.5" width="345.5" height="256" frameX="0" frameY="-27" frameWidth="380" frameHeight="283"/>
	<SubTexture name="Twi_Right_LASER instance 10001" x="1684" y="1637.5" width="358" height="277.5" frameX="-22" frameY="-5.5" frameWidth="380" frameHeight="283"/>
	<SubTexture name="Twi_Right_LASER instance 10002" x="2067" y="1637.5" width="342.5" height="282" frameX="-23.5" frameY="-1" frameWidth="380" frameHeight="283"/>
	<SubTexture name="Twi_Right_LASER instance 10003" x="2434.5" y="1637.5" width="341" height="283" frameX="-25" frameY="0" frameWidth="380" frameHeight="283"/>
	<SubTexture name="Twi_Right_LASER instance 10004" x="2800.5" y="1637.5" width="342.5" height="283" frameX="-24" frameY="0" frameWidth="380" frameHeight="283"/>
	<SubTexture name="Twi_Right_LASER instance 10005" x="3168" y="1637.5" width="338.5" height="282" frameX="-24" frameY="-1" frameWidth="380" frameHeight="283"/>
	<SubTexture name="Twi_Shoot_LASER instance 10000" x="3531.5" y="1637.5" width="378" height="245.5" frameX="0" frameY="-32.5" frameWidth="543" frameHeight="278"/>
	<SubTexture name="Twi_Shoot_LASER instance 10001" x="0" y="1945.5" width="382.5" height="245.5" frameX="0" frameY="-32.5" frameWidth="543" frameHeight="278"/>
	<SubTexture name="Twi_Shoot_LASER instance 10002" x="407.5" y="1945.5" width="466" height="242.5" frameX="-73" frameY="-35.5" frameWidth="543" frameHeight="278"/>
	<SubTexture name="Twi_Shoot_LASER instance 10003" x="898.5" y="1945.5" width="470" height="242.5" frameX="-73" frameY="-35.5" frameWidth="543" frameHeight="278"/>
	<SubTexture name="Twi_Shoot_LASER instance 10004" x="1393.5" y="1945.5" width="423.5" height="271.5" frameX="-83" frameY="-6.5" frameWidth="543" frameHeight="278"/>
	<SubTexture name="Twi_Shoot_LASER instance 10005" x="1842" y="1945.5" width="450" height="276.5" frameX="-83" frameY="-1.5" frameWidth="543" frameHeight="278"/>
	<SubTexture name="Twi_Shoot_LASER instance 10006" x="2317" y="1945.5" width="451.5" height="253" frameX="-83" frameY="-25" frameWidth="543" frameHeight="278"/>
	<SubTexture name="Twi_Shoot_LASER instance 10007" x="2793.5" y="1945.5" width="408.5" height="253" frameX="-83" frameY="-25" frameWidth="543" frameHeight="278"/>
	<SubTexture name="Twi_Shoot_LASER instance 10008" x="3227" y="1945.5" width="392.5" height="256" frameX="-76" frameY="-22" frameWidth="543" frameHeight="278"/>
	<SubTexture name="Twi_Shoot_LASER instance 10009" x="3644.5" y="1945.5" width="392.5" height="256" frameX="-76" frameY="-22" frameWidth="543" frameHeight="278"/>
	<SubTexture name="Twi_Shoot_LASER instance 10010" x="0" y="2247" width="361" height="277.5" frameX="-52.5" frameY="-0.5" frameWidth="543" frameHeight="278"/>
	<SubTexture name="Twi_Shoot_LASER instance 10011" x="386" y="2247" width="349.5" height="277.5" frameX="-52.5" frameY="-0.5" frameWidth="543" frameHeight="278"/>
	<SubTexture name="Twi_Shoot_LASER instance 10012" x="760.5" y="2247" width="274.5" height="259" frameX="-11.5" frameY="-19" frameWidth="543" frameHeight="278"/>
	<SubTexture name="Twi_Shoot_LASER instance 10013" x="1060" y="2247" width="274.5" height="259" frameX="-11.5" frameY="-19" frameWidth="543" frameHeight="278"/>
	<SubTexture name="Twi_Shoot_LASER instance 10014" x="1359.5" y="2247" width="269.5" height="274" frameX="-11" frameY="-4" frameWidth="543" frameHeight="278"/>
	<SubTexture name="Twi_Shoot_LASER instance 10015" x="1654" y="2247" width="269.5" height="273.5" frameX="-11" frameY="-4.5" frameWidth="543" frameHeight="278"/>
	<SubTexture name="Twi_Shoot_LASER instance 10016" x="1948.5" y="2247" width="271.5" height="277" frameX="-11" frameY="-1" frameWidth="543" frameHeight="278"/>
	<SubTexture name="Twi_Shoot_LASER instance 10017" x="2245" y="2247" width="271.5" height="277" frameX="-11" frameY="-1" frameWidth="543" frameHeight="278"/>
	<SubTexture name="Twi_Shoot_LASER instance 10018" x="2541.5" y="2247" width="271.5" height="278" frameX="-11" frameY="0" frameWidth="543" frameHeight="278"/>
	<SubTexture name="Twi_Shoot_LASER instance 10019" x="2838" y="2247" width="271.5" height="278" frameX="-11" frameY="0" frameWidth="543" frameHeight="278"/>
	<SubTexture name="Twi_Shoot_LASER instance 10020" x="3134.5" y="2247" width="271.5" height="276.5" frameX="-11" frameY="-1.5" frameWidth="543" frameHeight="278"/>
	<SubTexture name="Twi_Up_LASER instance 10000" x="3431" y="2247" width="292.5" height="256" frameX="0" frameY="-80.5" frameWidth="292.5" frameHeight="353.5"/>
	<SubTexture name="Twi_Up_LASER instance 10001" x="3748.5" y="2247" width="240.5" height="353.5" frameX="-43.5" frameY="0" frameWidth="292.5" frameHeight="353.5"/>
	<SubTexture name="Twi_Up_LASER instance 10002" x="0" y="2625.5" width="259.5" height="314" frameX="-23" frameY="-28.5" frameWidth="292.5" frameHeight="353.5"/>
	<SubTexture name="Twi_Up_LASER instance 10003" x="284.5" y="2625.5" width="261.5" height="300" frameX="-20" frameY="-38.5" frameWidth="292.5" frameHeight="353.5"/>
	<SubTexture name="Twi_Up_LASER instance 10004" x="571" y="2625.5" width="261.5" height="301" frameX="-20" frameY="-38" frameWidth="292.5" frameHeight="353.5"/>
	<SubTexture name="Twi_Up_LASER instance 10005" x="857.5" y="2625.5" width="261.5" height="304.5" frameX="-20.5" frameY="-35.5" frameWidth="292.5" frameHeight="353.5"/>
</TextureAtlas>
